[
    {
        "componentChunkName": "component---src-templates-index-js",
        "jsonName": "index",
        "path": "/"
    },
    {
        "componentChunkName": "component---src-templates-index-js",
        "jsonName": "2-de0",
        "path": "/2"
    },
    {
        "componentChunkName": "component---src-pages-404-js",
        "jsonName": "404-html-516",
        "path": "/404.html"
    },
    {
        "componentChunkName": "component---src-pages-404-js",
        "jsonName": "404-22d",
        "path": "/404/"
    },
    {
        "componentChunkName": "component---src-templates-page-js",
        "jsonName": "about-771",
        "path": "/about"
    },
    {
        "componentChunkName": "component---src-templates-page-js",
        "jsonName": "azeroth-weather-makingof-958",
        "path": "/azeroth-weather-makingof"
    },
    {
        "componentChunkName": "component---cache-dev-404-page-js",
        "jsonName": "dev-404-page-5f9",
        "path": "/dev-404-page/"
    },
    {
        "componentChunkName": "component---src-templates-page-js",
        "jsonName": "filesizes-551",
        "path": "/filesizes"
    },
    {
        "componentChunkName": "component---src-templates-page-js",
        "jsonName": "gitcredentials-48f",
        "path": "/gitcredentials"
    },
    {
        "componentChunkName": "component---src-templates-page-js",
        "jsonName": "hello-3ed",
        "path": "/hello"
    },
    {
        "componentChunkName": "component---src-templates-page-js",
        "jsonName": "js-functions-49a",
        "path": "/js-functions"
    },
    {
        "componentChunkName": "component---src-templates-page-js",
        "jsonName": "react-docker-development-f1d",
        "path": "/react-docker-development"
    },
    {
        "componentChunkName": "component---src-templates-tags-js",
        "jsonName": "tag-api-d36",
        "path": "/tag/API"
    },
    {
        "componentChunkName": "component---src-templates-tags-js",
        "jsonName": "tag-console-dba",
        "path": "/tag/console"
    },
    {
        "componentChunkName": "component---src-templates-tags-js",
        "jsonName": "tag-development-129",
        "path": "/tag/development"
    },
    {
        "componentChunkName": "component---src-templates-tags-js",
        "jsonName": "tag-docker-41a",
        "path": "/tag/docker"
    },
    {
        "componentChunkName": "component---src-templates-tags-js",
        "jsonName": "tag-firstpost-165",
        "path": "/tag/firstpost"
    },
    {
        "componentChunkName": "component---src-templates-tags-js",
        "jsonName": "tag-git-59f",
        "path": "/tag/git"
    },
    {
        "componentChunkName": "component---src-templates-tags-js",
        "jsonName": "tag-hello-c89",
        "path": "/tag/hello"
    },
    {
        "componentChunkName": "component---src-templates-tags-js",
        "jsonName": "tag-optimization-cb2",
        "path": "/tag/optimization"
    },
    {
        "componentChunkName": "component---src-templates-tags-js",
        "jsonName": "tag-personal-c7c",
        "path": "/tag/personal"
    },
    {
        "componentChunkName": "component---src-templates-tags-js",
        "jsonName": "tag-project-f6f",
        "path": "/tag/project"
    },
    {
        "componentChunkName": "component---src-templates-tags-js",
        "jsonName": "tag-rant-63f",
        "path": "/tag/rant"
    },
    {
        "componentChunkName": "component---src-templates-tags-js",
        "jsonName": "tag-react-ca0",
        "path": "/tag/react"
    },
    {
        "componentChunkName": "component---src-templates-tags-js",
        "jsonName": "tag-setup-67f",
        "path": "/tag/setup"
    },
    {
        "componentChunkName": "component---src-templates-tags-js",
        "jsonName": "tag-speed-fcc",
        "path": "/tag/speed"
    },
    {
        "componentChunkName": "component---src-templates-tags-js",
        "jsonName": "tag-twitch-070",
        "path": "/tag/twitch"
    },
    {
        "componentChunkName": "component---src-templates-tags-js",
        "jsonName": "tag-website-14c",
        "path": "/tag/website"
    },
    {
        "componentChunkName": "component---src-templates-tags-js",
        "jsonName": "tag-windows-234",
        "path": "/tag/windows"
    },
    {
        "componentChunkName": "component---src-templates-tags-js",
        "jsonName": "tag-wsl-6d2",
        "path": "/tag/wsl"
    },
    {
        "componentChunkName": "component---src-templates-page-js",
        "jsonName": "twitch-api-migration-30b",
        "path": "/twitch-api-migration"
    },
    {
        "componentChunkName": "component---src-templates-page-js",
        "jsonName": "website-speed-033",
        "path": "/website-speed"
    },
    {
        "componentChunkName": "component---src-templates-page-js",
        "jsonName": "wsl-2-issues-f1e",
        "path": "/wsl2-issues"
    }
]